{
  "2022-06-26": [
    {
      "day": "26/06/2022",
      "height": 40,
      "name": "Ngày nghỉ"
    }
  ],
  "2022-06-27": [
    
  ],
  "2022-06-28": [
    {
      "day": "28/06/2022",
      "height": 40,
      "name": "task3"
    },
     {
      "day": "28/06/2022",
      "height": 40,
      "name": "task34"
    },
  ],
  "2022-06-29": [
     {
      "day": "29/06/2022",
      "height": 40,
      "name": "task3"
    },
     {
      "day": "29/06/2022",
      "height": 40,
      "name": "task5"
    },
     {
      "day": "29/06/2022",
      "height": 40,
      "name": "task6"
    },
  ]
}
